regexhunter/__init__.py
regexhunter/hunter.py
regexhunter-1.2.dist-info/LICENSE
regexhunter-1.2.dist-info/METADATA
regexhunter-1.2.dist-info/WHEEL
regexhunter-1.2.dist-info/top_level.txt
regexhunter-1.2.dist-info/RECORD
