Metadata-Version: 2.1
Name: regexhunter
Version: 1.2
Summary: A small package allowing you to search for regex pre-formatted for you.
Home-page: https://github.com/SevenOfHurt/RegexHunter/
Author: Tom Moritz
Author-email: tom.moritz@outlook.fr
License: UNKNOWN
Platform: UNKNOWN
Classifier: Programming Language :: Python :: 3
Classifier: License :: OSI Approved :: MIT License
Classifier: Operating System :: OS Independent
